{
    "joinUsPrograms":[
        {
            "programName":"Program Name",
            "programLink":"/programs",
            "programDesc":" Lorem ipsum dolor sit, amet consectetur adipisicing elit. Exercitationem aliquam "
        },
        {
            "programName":"Program Name",
            "programLink":"/programs",
            "programDesc":" Lorem ipsum dolor sit, amet consectetur adipisicing elit. Exercitationem aliquam "
        },
        {
            "programName":"Program Name",
            "programLink":"/programs",
            "programDesc":" Lorem ipsum dolor sit, amet consectetur adipisicing elit. Exercitationem aliquam "
        }
        ,
        {
            "programName":"Program Name",
            "programLink":"/programs",
            "programDesc":" Lorem ipsum dolor sit, amet consectetur adipisicing elit. Exercitationem aliquam "
        }
    ]
}